image2image_io/__init__.py
image2image_io/config.py
image2image_io/enums.py
image2image_io/exceptions.py
image2image_io/merge.py
image2image_io/py.typed
image2image_io/wrapper.py
image2image_io/cli/__init__.py
image2image_io/cli/_common.py
image2image_io/cli/convert.py
image2image_io/cli/czi2tiff.py
image2image_io/cli/merge.py
image2image_io/cli/thumbnail.py
image2image_io/cli/transform.py
image2image_io/models/__init__.py
image2image_io/models/base.py
image2image_io/models/merge.py
image2image_io/models/preprocess.py
image2image_io/models/transform.py
image2image_io/readers/__init__.py
image2image_io/readers/_base_reader.py
image2image_io/readers/_czi.py
image2image_io/readers/array_reader.py
image2image_io/readers/coordinate_reader.py
image2image_io/readers/czi_reader.py
image2image_io/readers/geojson_utils.py
image2image_io/readers/points_reader.py
image2image_io/readers/shapes_reader.py
image2image_io/readers/tiff_reader.py
image2image_io/readers/tiff_utils.py
image2image_io/readers/utilities.py
image2image_io/utils/__init__.py
image2image_io/utils/_appdirs.py
image2image_io/utils/_test.py
image2image_io/utils/itk.py
image2image_io/utils/lazy.py
image2image_io/utils/mask.py
image2image_io/utils/utilities.py
image2image_io/utils/warp.py
image2image_io/writers/__init__.py
image2image_io/writers/merge_tiff_writer.py
image2image_io/writers/tiff_writer.py
image2image_io-0.2.0.dist-info/METADATA
image2image_io-0.2.0.dist-info/WHEEL
image2image_io-0.2.0.dist-info/entry_points.txt
image2image_io-0.2.0.dist-info/licenses/LICENSE
image2image_io-0.2.0.dist-info/RECORD
