Metadata-Version: 2.4
Name: image2image-io
Version: 0.2.0
Summary: Image readers and writers for image2image.
Project-URL: homepage, https://github.com/vandeplaslab/image2image-io
Project-URL: repository, https://github.com/vandeplaslab/image2image-io
Author-email: "Lukasz G. Migas" <lukas.migas@yahoo.com>
License: BSD 3-Clause License
License-File: LICENSE
Classifier: Development Status :: 3 - Alpha
Classifier: Intended Audience :: Education
Classifier: Intended Audience :: Science/Research
Classifier: License :: OSI Approved :: BSD License
Classifier: Natural Language :: English
Classifier: Operating System :: MacOS
Classifier: Operating System :: Microsoft :: Windows
Classifier: Operating System :: POSIX
Classifier: Operating System :: Unix
Classifier: Programming Language :: Python :: 3
Classifier: Programming Language :: Python :: 3.10
Classifier: Programming Language :: Python :: 3.11
Classifier: Programming Language :: Python :: 3.12
Classifier: Programming Language :: Python :: 3.13
Classifier: Topic :: Scientific/Engineering
Classifier: Topic :: Scientific/Engineering :: Bio-Informatics
Classifier: Topic :: Scientific/Engineering :: Information Analysis
Classifier: Topic :: Scientific/Engineering :: Visualization
Classifier: Topic :: Utilities
Classifier: Typing :: Typed
Requires-Python: >=3.10
Requires-Dist: aicsimageio
Requires-Dist: appdirs
Requires-Dist: czifile
Requires-Dist: dicttoxml
Requires-Dist: fastparquet
Requires-Dist: geojson
Requires-Dist: h5py
Requires-Dist: imagecodecs
Requires-Dist: imzy
Requires-Dist: koyo>=0.3.0
Requires-Dist: numcodecs<0.16.0; python_version < '3.13'
Requires-Dist: numcodecs>=0.16.0; python_version >= '3.13'
Requires-Dist: ome-types
Requires-Dist: opencv-python
Requires-Dist: pint
Requires-Dist: pyarrow
Requires-Dist: pydantic>=2
Requires-Dist: rasterio
Requires-Dist: scikit-image
Requires-Dist: shapely
Requires-Dist: simpleitk
Requires-Dist: tifffile
Requires-Dist: zarr
